LICENSE.md
MANIFEST.in
README.md
requirements.txt
setup.py
OSfooler_ng.egg-info/PKG-INFO
OSfooler_ng.egg-info/SOURCES.txt
OSfooler_ng.egg-info/dependency_links.txt
OSfooler_ng.egg-info/entry_points.txt
OSfooler_ng.egg-info/requires.txt
OSfooler_ng.egg-info/top_level.txt
osfooler_ng/__init__.py
osfooler_ng/module_p0f.py
osfooler_ng/osfooler_ng.py
osfooler_ng/dep/nmap-os-db
osfooler_ng/dep/p0f.fp
osfooler_ng/dep/p0fa.fp
osfooler_ng/dep/p0fr.fp