Metadata-Version: 2.1
Name: OSfooler-ng
Version: 1.0a0
Summary: OSfooler-ng prevents remote OS active/passive fingerprinting by tools like nmap or p0f
Home-page: https://github.com/segofensiva/OSfooler-ng
Author: Jaime Sanchez (@segofensiva)
Author-email: jsanchez@seguridadofensiva.com
License: UNKNOWN
Platform: UNKNOWN
Classifier: Development Status :: 4 - Beta
Classifier: Environment :: Console
Classifier: Operating System :: POSIX :: Linux
Classifier: Topic :: System :: Networking
Classifier: Programming Language :: Python
Classifier: Topic :: Security
Classifier: License :: OSI Approved :: GNU General Public License v3 (GPLv3)
